{"id":35986,"path":"Assets\/_Project\/Models\/Elements\/Pins\/57_Pin_Sword.fbx","assetBundleId":-1,"components":[{"type":1,"id":37488,"data":[-1.60973393917084,0.00544708967208862,-0.000419437885284424,1,1,1,0,0,0,1]}],"children":[{"id":39544,"path":"Assets\/_Project\/Models\/Elements\/Pins\/57_Pin_Sword.fbx","assetBundleId":-1,"components":[{"type":1,"id":38636,"data":[1.19356119632721,-0.00544708967208862,0.000419437885284424,1,1,1,0,0,0,1]},{"type":56,"id":40390,"data":[38,40394]},{"type":52,"id":40392,"data":[null,null,1,4,34608,[4,34608],1,1,0,0,-1,-1,1,1,0,0,1,1]}],"children":[],"data":["Pin_Sword_body",0,1,0,0]},{"id":39542,"path":"Assets\/_Project\/Models\/Elements\/Pins\/57_Pin_Sword.fbx","assetBundleId":-1,"components":[{"type":1,"id":38638,"data":[1.66786921024323,-8.67361737988404E-19,0,1,1,1,0,0,0,1]},{"type":56,"id":40386,"data":[38,40918]},{"type":52,"id":40388,"data":[null,null,1,4,34608,[4,34608],1,1,0,0,-1,-1,1,1,0,0,1,1]}],"children":[],"data":["Pin_Sword_head",0,1,0,0]},{"id":39540,"path":"Assets\/_Project\/Models\/Elements\/Pins\/57_Pin_Sword.fbx","assetBundleId":-1,"components":[{"type":1,"id":38640,"data":[-1.80697906017303,-0.0241825133562088,0.00120216608047485,1,1,1,0,0,0,1]},{"type":56,"id":40382,"data":[38,40396]},{"type":52,"id":40384,"data":[null,null,1,4,34608,[4,34608],1,1,0,0,-1,-1,1,1,0,0,1,1]}],"children":[],"data":["Pin_Sword_tail",0,1,0,0]}],"data":["57_Pin_Sword",0,1,0,0]}